sqlalchemy_things/__init__.py
sqlalchemy_things/column_types/__init__.py
sqlalchemy_things/column_types/uuid.py
sqlalchemy_things/declarative/__init__.py
sqlalchemy_things/declarative/base.py
sqlalchemy_things/declarative/primary_keys.py
sqlalchemy_things/pagination.py
sqlalchemy_things/py.typed
sqlalchemy_things-1.2.0.dist-info/LICENSE
sqlalchemy_things-1.2.0.dist-info/METADATA
sqlalchemy_things-1.2.0.dist-info/WHEEL
sqlalchemy_things-1.2.0.dist-info/RECORD
