Metadata-Version: 2.3
Name: sqlalchemy-things
Version: 1.2.0
Summary: Utility collection for development with SQLalchemy ORM.
License: MIT
Keywords: sqlalchemy
Author: Ruslan Ilyasovich Gilfanov
Author-email: rigilfanov@yandex.ru>
Maintainer: Ruslan Ilyasovich Gilfanov
Maintainer-email: rigilfanov@yandex.ru>
Requires-Python: >=3.9,<3.15
Classifier: Development Status :: 5 - Production/Stable
Classifier: License :: OSI Approved :: MIT License
Classifier: Operating System :: OS Independent
Classifier: Programming Language :: Python
Classifier: Programming Language :: Python :: 3
Classifier: Programming Language :: Python :: 3.9
Classifier: Programming Language :: Python :: 3.10
Classifier: Programming Language :: Python :: 3.11
Classifier: Programming Language :: Python :: 3.12
Classifier: Programming Language :: Python :: 3.13
Classifier: Programming Language :: Python :: 3.14
Classifier: Topic :: Database
Classifier: Topic :: Database :: Front-Ends
Classifier: Topic :: Software Development
Classifier: Topic :: Software Development :: Libraries
Classifier: Topic :: Software Development :: Libraries :: Python Modules
Provides-Extra: mysql
Provides-Extra: postgresql
Provides-Extra: sqlite
Requires-Dist: aiomysql (>=0.3.2,<1) ; extra == "mysql"
Requires-Dist: aiosqlite (>=0.22.1,<1) ; extra == "sqlite"
Requires-Dist: asyncpg (>=0.31.0,<1) ; extra == "postgresql"
Requires-Dist: sqlalchemy (>=2.0.45,<3)
